esv_api/__init__.py
esv_api/audio.py
esv_api/html.py
esv_api/method.py
esv_api/passage.py
esv_api/search.py
esv_api/text.py
esv_api_samhaswon-0.0.2.dist-info/LICENSE
esv_api_samhaswon-0.0.2.dist-info/METADATA
esv_api_samhaswon-0.0.2.dist-info/WHEEL
esv_api_samhaswon-0.0.2.dist-info/top_level.txt
esv_api_samhaswon-0.0.2.dist-info/RECORD
