Metadata-Version: 2.1
Name: esv-api-samhaswon
Version: 0.0.2
Summary: A Python package for interfacing with the ESV API
Author: Samuel Howard
License: GNU GENERAL PUBLIC LICENSE
Project-URL: Homepage, https://github.com/samhaswon/esv_api
Project-URL: Bug Tracker, https://github.com/samhaswon/esv_api/issues
Keywords: esv_api,esv,bible_api,bible
Classifier: Programming Language :: Python :: 3
Classifier: Operating System :: OS Independent
Requires-Python: >=3.7
License-File: LICENSE
Requires-Dist: requests
Requires-Dist: multipledispatch
